Metadata-Version: 1.0
Name: hexapodo-utils
Version: 0.1
Summary: Hexapodo's functions
Home-page: https://github.com/datankai/hexapodo-utils
Author: juandatank
Author-email: juan@datank.ai
License: MIT
Platform: UNKNOWN
